LICENSE
MANIFEST.in
README.rst
setup.py
berserker_resolver/__init__.py
berserker_resolver/resolver.py
berserker_resolver/utils.py
berserker_resolver.egg-info/PKG-INFO
berserker_resolver.egg-info/SOURCES.txt
berserker_resolver.egg-info/dependency_links.txt
berserker_resolver.egg-info/not-zip-safe
berserker_resolver.egg-info/pbr.json
berserker_resolver.egg-info/requires.txt
berserker_resolver.egg-info/top_level.txt