Metadata-Version: 1.1
Name: berserker-resolver
Version: 2.0.1
Summary: Fast mass dns resolver which can bypass loadbalancers
Home-page: https://github.com/DmitryFillo/berserker_resolver
Author: Dmitry Fillo
Author-email: fillo@fillo.me
License: BSD
Keywords: dns resolver berserker loadbalancer
Platform: any
Classifier: Development Status :: 5 - Production/Stable
Classifier: Topic :: Internet :: Name Service (DNS)
Classifier: Topic :: Utilities
Classifier: Intended Audience :: Developers
Classifier: License :: OSI Approved :: BSD License
Classifier: Programming Language :: Python :: 2.6
Classifier: Programming Language :: Python :: 2.7
Classifier: Programming Language :: Python :: 3.2
Classifier: Programming Language :: Python :: 3.3
Classifier: Programming Language :: Python :: 3.4
